jack_midi_monitor/__init__.py
jack_midi_monitor/__main__.py
jack_midi_monitor/gui.py
jack_midi_monitor/res/gui.ui
jack_midi_monitor-1.1.2.dist-info/entry_points.txt
jack_midi_monitor-1.1.2.dist-info/LICENSE
jack_midi_monitor-1.1.2.dist-info/WHEEL
jack_midi_monitor-1.1.2.dist-info/METADATA
jack_midi_monitor-1.1.2.dist-info/RECORD
