Metadata-Version: 2.1
Name: jack_midi_monitor
Version: 1.1.2
Summary: Provides a means to monitor midi events from a Jack client.
Author-email: Leon Dionne <ldionne@dridesign.sh.cn>
Classifier: License :: OSI Approved :: GNU General Public License v3 or later (GPLv3+)
Classifier: Programming Language :: Python
Classifier: Programming Language :: Python :: 3.10
Classifier: Topic :: Multimedia :: Sound/Audio :: MIDI
Classifier: Topic :: Utilities
Requires-Dist: JACK-Client
Requires-Dist: midi_notes
Requires-Dist: PyQt5
Requires-Dist: soso_qt_extras >= 1.2.0
